AUTHORS.rst
CONTRIBUTING.rst
HISTORY.rst
LICENSE
MANIFEST.in
README.rst
setup.cfg
setup.py
docs/Makefile
docs/authors.rst
docs/conf.py
docs/contributing.rst
docs/history.rst
docs/index.rst
docs/installation.rst
docs/make.bat
docs/readme.rst
docs/usage.rst
ffio/__init__.py
ffio/ffio.py
ffio.egg-info/PKG-INFO
ffio.egg-info/SOURCES.txt
ffio.egg-info/dependency_links.txt
ffio.egg-info/not-zip-safe
ffio.egg-info/top_level.txt
tests/__init__.py
tests/test_ffio.py