Metadata-Version: 1.2
Name: ffio
Version: 0.1.0
Summary: test description
Home-page: https://github.com/aamini/ffio
Author: Alexander Amini
Author-email: amini@mit.edu
License: MIT license
Keywords: ffio
Platform: UNKNOWN
Classifier: Development Status :: 2 - Pre-Alpha
Classifier: Intended Audience :: Developers
Classifier: License :: OSI Approved :: MIT License
Classifier: Natural Language :: English
Classifier: Programming Language :: Python :: 3
Classifier: Programming Language :: Python :: 3.5
Classifier: Programming Language :: Python :: 3.6
Classifier: Programming Language :: Python :: 3.7
Classifier: Programming Language :: Python :: 3.8
Requires-Python: >=3.5
